purehash/__init__.py
purehash/_common.py
purehash/_md5.py
purehash/_sha1.py
purehash/_sha2.py
purehash/_util.py
purehash/algorithms/__init__.py
purehash/algorithms/_md5.py
purehash/algorithms/_sha1.py
purehash/algorithms/_sha2.py
purehash/tests/__init__.py
purehash/tests/test_md5.py
purehash/tests/test_sha1.py
purehash/tests/test_sha2.py
purehash/tests/test_util.py
purehash-1.1.0.dist-info/LICENSE
purehash-1.1.0.dist-info/METADATA
purehash-1.1.0.dist-info/WHEEL
purehash-1.1.0.dist-info/top_level.txt
purehash-1.1.0.dist-info/RECORD
